SM2ST/SMLED.py
SM2ST/Train_SMLED.py
SM2ST/__init__.py
SM2ST/dataset.py
SM2ST/gatv2_conv.py
SM2ST/rectification.py
SM2ST/utils.py
sm2st-0.0.1.dist-info/LICENSE.txt
sm2st-0.0.1.dist-info/METADATA
sm2st-0.0.1.dist-info/WHEEL
sm2st-0.0.1.dist-info/top_level.txt
sm2st-0.0.1.dist-info/RECORD
