Metadata-Version: 2.1
Name: SM2ST
Version: 0.0.1
Summary: SM2ST: Automatic registration of spatial metabolome and spatial transcriptome via adversarial autoencoders
Home-page: https://github.com/binbin-coder/SM2ST
Author: LLX
Author-email: llx_1910@163.com
Classifier: Programming Language :: Python :: 3
Classifier: License :: OSI Approved :: MIT License
Classifier: Operating System :: OS Independent
Requires-Python: >=3.8
License-File: LICENSE.txt
